cacoepy/__init__.py
cacoepy/aligner.py
cacoepy/metric.py
cacoepy/core/ARPAbet_similarity_matrix.py
cacoepy/core/Needleman_Wunsch.py
cacoepy/core/__init__.py
cacoepy/core/aligner_tools.py
cacoepy/core/exceptions.py
cacoepy/core/utils.py
cacoepy-1.1.0.dist-info/METADATA
cacoepy-1.1.0.dist-info/WHEEL
cacoepy-1.1.0.dist-info/top_level.txt
cacoepy-1.1.0.dist-info/RECORD
