Metadata-Version: 2.1
Name: cacoepy
Version: 1.1.0
Summary: A small collection of tools related to mispronunciation detection and diagnosis (MDD) systems.
Home-page: https://github.com/Brono25/cacoepy.git
Author: Bronston Ashford
Author-email: bronston.a@gmail.com
Classifier: Programming Language :: Python :: 3
Classifier: License :: OSI Approved :: MIT License
Classifier: Operating System :: OS Independent
Requires-Python: >=3.10
Requires-Dist: numpy
